piped_manhole
